twitsent/Results-Page-TweetSA.html
twitsent/__init__.py
twitsent/__main__.py
twitsent/dateselect.py
twitsent/makescript.py
twitsent/parse_sentiment.py
twitsent/plot_sent.py
twitsent/sentiment_comparisongraph.png
twitsent/store_data.py
twitsent/twitterquery.py
twitsent/storedqueries/archivedsenti_7.31.22_8.1.22_10_240_.csv
twitsent/storedqueries/archivedsenti_7.31.22_8.1.22_10_240_sample.csv
twitsent/storedqueries/archivedtweet_7.31.22_8.1.22_10_240_.csv
twitsent/storedqueries/archivedtweet_7.31.22_8.1.22_10_240_sample.csv
twitsent/storedqueries/senti_7.31.22_8.1.22_10_240_.csv
twitsent/storedqueries/senti_7.31.22_8.1.22_10_240_sample.csv
twitsent/storedqueries/tweet_7.31.22_8.1.22_10_240_.csv
twitsent/storedqueries/tweet_7.31.22_8.1.22_10_240_sample.csv
twitsent-1.0.7.dist-info/METADATA
twitsent-1.0.7.dist-info/WHEEL
twitsent-1.0.7.dist-info/licenses/LICENSE
twitsent-1.0.7.dist-info/RECORD
