Metadata-Version: 2.1
Name: twitsent
Version: 1.0.7
Summary: A package for tracking historical sentiment data from Twitter over certain keywords
Project-URL: Homepage, https://github.com/pypa/twitsent
Project-URL: Bug Tracker, https://github.com/pypa/twitsent/issues
Author-email: Mitchell Hoikka <mitchell.hoikka1@gmail.com>
License: Copyright (c) 2018 The Python Packaging Authority
Classifier: License :: OSI Approved :: MIT License
Classifier: Operating System :: OS Independent
Classifier: Programming Language :: Python :: 3
Requires-Python: >=3.7
Requires-Dist: clean-text>=0.6.0
Requires-Dist: matplotlib>=3.5.2
Requires-Dist: nltk>=3.5
Requires-Dist: pymannkendall>=1.4.2
Requires-Dist: requests>=2.27.1
Requires-Dist: tkcalendar>=1.6.1
Requires-Dist: unidecode>=1.3.4
